materia_clase/Ejemplos/Latches_y_Flip_Flops/gated_rsff.v
//`timescale 1us / 1ns

//Set-Reset Latch
module srff (s, r, q, qb);
  parameter Ta = 1,
            Tb = 1,
            Tbas = 1;
  input s, r;
  output q, qb;
  wire aux_q, aux_qb;

  nor #(Ta) c1 (qb, s, q);
  nor #(Tb) c2 (q, r, qb);

  nor #(Tbas) aux1 (aux_qb, s, q);
  nor #(Tbas) aux2 (aux_q, r, qb);
  
  //Codigo de instrumentacion ****************************************************************************
  //Medicion de tiempos de propagacion
  time Ts_q;
  //Medicion de tiempo de propagacion de entrada set a salida q
  always @ (posedge s)
    begin
	  if (testbench.s_rise == 1 && testbench.r_rise == 0 && q == 0)
	    begin
	      @ (posedge q);
	      Ts_q = $time - testbench.TsCH;
	      $display($time,,"** - %m - Tiempo de propagacion de set a q: %0t", Ts_q);
		end
	end

  //Avisa cuando las salidas del FF no son complementarias
  always @ (negedge (q ^ qb))
    $display($time,,"** - %m - Salidas q y qb son iguales.");

  //Avisa cuando las salidas del FF no son complementarias
  always @ (posedge (q ^ qb))
    $display($time,,"** - %m - Salidas q y qb son complementarias.");

endmodule

//Gated Set-Reset Latch
module gsrff (s, r, g, q, qb);
  parameter Ta = 1,
            Tb = 1,
            Tbas = 1;
  input s, r, g;
  output q, qb;

  nor #(Ta) c1 (qb, x, q);
  nor #(Tb) c2 (q, y, qb);
  and #(Tbas) c3 (x, s, g);
  and #(Tbas) c4 (y, r, g);

endmodule

//Set-Reset Master/Slave Flip Flop
module MSff (s, r, clk, q, qb);
  parameter Ta = 1,
            Tb = 1,
            Tbas = 1;
  input s, r, clk;
  output q, qb;

  gsrff #(Ta, Tb, Tbas) master (s, r, clk, q_m, qb_m);
  not #(Tbas) inv1 (clkb, clk);
  gsrff #(Ta, Tb, Tbas) slave (q_m, qb_m, clkb, q, qb);

endmodule

//Edge-Triggered Set-Reset Flip Flop
module ETff (s, r, clk, q, qb);
  parameter Ta = 1,
            Tb = 1,
            Tbas = 1;
  input s, r, clk;
  output q, qb;

  //Main latch
  nor #(Ta) ns1 (qb, qs, q);
  nor #(Tb) nr2 (q, qr, qb);

  //Set side input latch
  nor #(Tbas) ns3 (qsb, s, sblk, qs);
  nor #(Tbas) ns4 (qs, qsb, qr, clk);

  //Reset side input latch
  nor #(Tbas) nr5 (qrb, r, rblk, qr);
  nor #(Tbas) nr6 (qr, qrb, qs, clk);

  //Blocking logic for set and reset side
  nor #(Tbas) ns7 (sblk, qb, r);
  nor #(Tbas) nr8 (rblk, q, s);

endmodule

//Top Module
module testbench;
  reg s, r, g;
  reg [1:0] vecs_entrada[0:25];
  reg [4:0] i;

//Dispositivos con los retardos balanceados - Estos deben oscilar
  srff  #(20, 20, 19) ff0 (s, r,    q_rs_bal,  qb_rs_bal);
  gsrff #(20, 20, 19) ff1 (s, r, g, q_grs_bal, qb_grs_bal);
  MSff  #(20, 20, 19) ff2 (s, r, g, q_MS_bal,  qb_MS_bal);
  ETff  #(20, 20, 19) ff3 (s, r, g, q_ET_bal,  qb_ET_bal);

//Dispositivos con Ta ligeramente mayor que Tb - No oscila, salida q se mantiene y estabiliza al dispositivo
  srff  #(21, 20, 19) ff4 (s, r,    q_rs_Ta21,  qb_rs_Ta21);
  gsrff #(21, 20, 19) ff5 (s, r, g, q_grs_Ta21, qb_grs_Ta21);
  MSff  #(21, 20, 19) ff6 (s, r, g, q_MS_Ta21,  qb_MS_Ta21);
  ETff  #(21, 20, 19) ff7 (s, r, g, q_ET_Ta21,  qb_ET_Ta21);

//Dispositivos con Tb ligeramente mayor que Ta - No oscila, salida qb se mantiene y estabiliza al dispositivo
  srff  #(20, 21, 19) ff8  (s, r,    q_rs_Tb21,  qb_rs_Tb21);
  gsrff #(20, 21, 19) ff9  (s, r, g, q_grs_Tb21, qb_grs_Tb21);
  MSff  #(20, 21, 19) ff10 (s, r, g, q_MS_Tb21,  qb_MS_Tb21);
  ETff  #(20, 21, 19) ff11 (s, r, g, q_ET_Tb21,  qb_ET_Tb21);

//Dispositivos con Ta mucho mayor que Tb - No oscila, salida q se mantiene y estabiliza al dispositivo
  srff  #(66, 20, 19) ff12 (s, r,    q_rs_Ta66,  qb_rs_Ta66);
  gsrff #(66, 20, 19) ff13 (s, r, g, q_grs_Ta66, qb_grs_Ta66);
  MSff  #(66, 20, 19) ff14 (s, r, g, q_MS_Ta66,  qb_MS_Ta66);
  ETff  #(66, 20, 19) ff15 (s, r, g, q_ET_Ta66,  qb_ET_Ta66);

//Dispositivos con Tb mucho mayor que Ta - No oscila, salida qb se mantiene y estabiliza al dispositivo
  srff  #(20, 66, 19) ff16 (s, r,    q_rs_Tb66,  qb_rs_Tb66);
  gsrff #(20, 66, 19) ff17 (s, r, g, q_grs_Tb66, qb_grs_Tb66);
  MSff  #(20, 66, 19) ff18 (s, r, g, q_MS_Tb66,  qb_MS_Tb66);
  ETff  #(20, 66, 19) ff19 (s, r, g, q_ET_Tb66,  qb_ET_Tb66);

  initial
    begin
      //Prepare el archivo *.vcd
      $dumpfile ("gated_sr_ff.vcd");
      $dumpvars;
      //Lea los vectores de entrada
      $readmemb ("vecs_entrada.dat", vecs_entrada);
	  //Iniciacion de algunas variables de instrumentacion
	  TsCH_old = $time; //Almacena el ultimo tiempo en que cambio la senal s
	  TrCH_old = $time; //Almacena el ultimo tiempo en que cambio la senal r
      //Inice la secuencia de entrada
      //Borde creciente del reloj coincide con cambio de entradas s y r
      #1000
      i = 0;
      #0 g = 1; //t3
      {s, r} = vecs_entrada[i];
      #21 g = 0; //t1
      #979 g = 1; //t2
      for (i = 1; i < 26; i = i + 1)
        begin
          #0 g = 1; //t3
          {s, r} = vecs_entrada[i];
          #21 g = 0; //t1
          #979 g = 1; //t2
        end
      //Cambio de entradas s y r antes del borde decreciente
      #1000
      i = 0;
      #481 g = 1; //t3
      {s, r} = vecs_entrada[i];
      #19 g = 0;  //t1 = Tiempo antes del borde decreciente
      #500 g = 1; //t2
      for (i = 1; i < 26; i = i + 1)
        begin
          #481 g = 1; //t3
          {s, r} = vecs_entrada[i];
          #19 g = 0;  //t1 = Tiempo antes del borde decreciente
          #500 g =1;  //t2
        end
      //Cambio de entradas s y r despues del borde decreciente
      #1000
      i = 0;
      #1 g = 0; //t3 = Tiempo despues del borde decreciente
      {s, r} = vecs_entrada[i];
      #499 g = 1;  //t1
      #500 g = 0; //t2
      for (i = 1; i < 26; i = i + 1)
        begin
          #1 g = 0; //t3 = Tiempo despues del borde decreciente
          {s, r} = vecs_entrada[i];
          #499 g = 1;  //t1
          #500 g =0;  //t2
        end
      $finish;
    end
	  
  //Codigo de instrumentacion ****************************************************************************
  //Variables para guardar el tiempo en que cambian las senales r, s, y g.
  time TsCH, TrCH;
  reg s_rise, r_rise;
  
  //Deteccion de flancos en entrada s
  always @ (negedge s)  //Detecta flancos decrecientes en s y registra tiempo
    begin
	  TsCH = $time;
	  s_rise = 0;
	end
  always @ (posedge s)  //Detecta flancos crecientes en s y registra tiempo
    begin
	  TsCH = $time;
	  s_rise = 1;
	end
	
  //Deteccion de flancos en entrada r
  always @ (negedge r)  //Detecta flancos decrecientes en r y registra tiempo
    begin
	  TrCH = $time;
	  r_rise = 0;
	end
  always @ (posedge r)  //Detecta flancos crecientes en r y registra tiempo
    begin
	  TrCH = $time;
	  r_rise = 1;
	end
	
  //Establece cual deberia ser el estado de q y qb partiendo de los cambios en s y r
  time TsCH_old, TrCH_old;
  reg sr_both;
  always @ (TsCH or TrCH)
    begin
	  //Revisar cuales entradas cambiaron y actualizar registro de s y r
	  if (TsCH > TsCH_old && TrCH > TrCH_old) //Ambas entradas cambiaron
	    begin
		  $display("** - Cambio en s(%0t)= %b y r(%0t)= %b.",TsCH,s,TrCH,r);
		  sr_both = 1; //Ambas cambiaron
	      TsCH_old = TsCH;
	      TrCH_old = TrCH;
		end
	  else if (TsCH > TsCH_old) //Solo cambio la senal s
	    begin
	      $display("** - Cambio en s(%0t)= %b.",TsCH,s);
		  sr_both = 0; //Solo una cambio
	      TsCH_old = TsCH;
		end
	  else //Solo cambio la senal r
	    begin
	      $display("** - Cambio en r(%0t)= %b.",TrCH,r);
		  sr_both = 0; //Solo una cambio
	      TrCH_old = TrCH;
		end
		
	  //Valoracion de la salida esperada del latch
	  if (s_rise == 1 && r_rise == 1)
		$display("** - Salidas q y qb ambas a 0.");
	  else if (s_rise == 0 && r_rise == 0 && sr_both == 1)
		$display("** - Salidas q y qb pueden oscilar.");
	  else if (s_rise == 0 && r_rise == 0 && sr_both == 0)
		$display("** - Salidas q y qb mantienen valor anterior.");
	  else if (s_rise == 1 && r_rise == 0)
		$display("** - Salidas correctas q=1 y qb=0.");
	  else if (s_rise == 0 && r_rise == 1)
		$display("** - Salidas correctas q=0 y qb=1.");
	  else
		$display("**ERROR** - Todas las combinaciones estan consideradas.");
		
	end
  
endmodule

materia_clase/Ejemplos/Latches_y_Flip_Flops/gated_sr_ff.vcd
$date
	Mon Apr 19 23:08:44 2010
$end
$version
	Icarus Verilog
$end
$timescale
	1s
$end
$scope module testbench $end
$var wire 1 ! q_ET_Ta21 $end
$var wire 1 " q_ET_Ta66 $end
$var wire 1 # q_ET_Tb21 $end
$var wire 1 $ q_ET_Tb66 $end
$var wire 1 % q_ET_bal $end
$var wire 1 & q_MS_Ta21 $end
$var wire 1 ' q_MS_Ta66 $end
$var wire 1 ( q_MS_Tb21 $end
$var wire 1 ) q_MS_Tb66 $end
$var wire 1 * q_MS_bal $end
$var wire 1 + q_grs_Ta21 $end
$var wire 1 , q_grs_Ta66 $end
$var wire 1 - q_grs_Tb21 $end
$var wire 1 . q_grs_Tb66 $end
$var wire 1 / q_grs_bal $end
$var wire 1 0 q_rs_Ta21 $end
$var wire 1 1 q_rs_Ta66 $end
$var wire 1 2 q_rs_Tb21 $end
$var wire 1 3 q_rs_Tb66 $end
$var wire 1 4 q_rs_bal $end
$var wire 1 5 qb_ET_Ta21 $end
$var wire 1 6 qb_ET_Ta66 $end
$var wire 1 7 qb_ET_Tb21 $end
$var wire 1 8 qb_ET_Tb66 $end
$var wire 1 9 qb_ET_bal $end
$var wire 1 : qb_MS_Ta21 $end
$var wire 1 ; qb_MS_Ta66 $end
$var wire 1 < qb_MS_Tb21 $end
$var wire 1 = qb_MS_Tb66 $end
$var wire 1 > qb_MS_bal $end
$var wire 1 ? qb_grs_Ta21 $end
$var wire 1 @ qb_grs_Ta66 $end
$var wire 1 A qb_grs_Tb21 $end
$var wire 1 B qb_grs_Tb66 $end
$var wire 1 C qb_grs_bal $end
$var wire 1 D qb_rs_Ta21 $end
$var wire 1 E qb_rs_Ta66 $end
$var wire 1 F qb_rs_Tb21 $end
$var wire 1 G qb_rs_Tb66 $end
$var wire 1 H qb_rs_bal $end
$var reg 64 I TrCH [63:0] $end
$var reg 64 J TrCH_old [63:0] $end
$var reg 64 K TsCH [63:0] $end
$var reg 64 L TsCH_old [63:0] $end
$var reg 1 M g $end
$var reg 5 N i [4:0] $end
$var reg 1 O r $end
$var reg 1 P r_rise $end
$var reg 1 Q s $end
$var reg 1 R s_rise $end
$var reg 1 S sr_both $end
$scope module ff0 $end
$var wire 1 T aux_q $end
$var wire 1 U aux_qb $end
$var wire 1 4 q $end
$var wire 1 H qb $end
$var wire 1 V r $end
$var wire 1 W s $end
$var reg 64 X Ts_q [63:0] $end
$upscope $end
$scope module ff1 $end
$var wire 1 Y g $end
$var wire 1 / q $end
$var wire 1 C qb $end
$var wire 1 V r $end
$var wire 1 W s $end
$var wire 1 Z x $end
$var wire 1 [ y $end
$upscope $end
$scope module ff2 $end
$var wire 1 Y clk $end
$var wire 1 \ clkb $end
$var wire 1 * q $end
$var wire 1 ] q_m $end
$var wire 1 > qb $end
$var wire 1 ^ qb_m $end
$var wire 1 V r $end
$var wire 1 W s $end
$scope module master $end
$var wire 1 Y g $end
$var wire 1 ] q $end
$var wire 1 ^ qb $end
$var wire 1 V r $end
$var wire 1 W s $end
$var wire 1 _ x $end
$var wire 1 ` y $end
$upscope $end
$scope module slave $end
$var wire 1 \ g $end
$var wire 1 * q $end
$var wire 1 > qb $end
$var wire 1 ^ r $end
$var wire 1 ] s $end
$var wire 1 a x $end
$var wire 1 b y $end
$upscope $end
$upscope $end
$scope module ff3 $end
$var wire 1 Y clk $end
$var wire 1 % q $end
$var wire 1 9 qb $end
$var wire 1 c qr $end
$var wire 1 d qrb $end
$var wire 1 e qs $end
$var wire 1 f qsb $end
$var wire 1 V r $end
$var wire 1 g rblk $end
$var wire 1 W s $end
$var wire 1 h sblk $end
$upscope $end
$scope module ff4 $end
$var wire 1 i aux_q $end
$var wire 1 j aux_qb $end
$var wire 1 0 q $end
$var wire 1 D qb $end
$var wire 1 V r $end
$var wire 1 W s $end
$var reg 64 k Ts_q [63:0] $end
$upscope $end
$scope module ff5 $end
$var wire 1 Y g $end
$var wire 1 + q $end
$var wire 1 ? qb $end
$var wire 1 V r $end
$var wire 1 W s $end
$var wire 1 l x $end
$var wire 1 m y $end
$upscope $end
$scope module ff6 $end
$var wire 1 Y clk $end
$var wire 1 n clkb $end
$var wire 1 & q $end
$var wire 1 o q_m $end
$var wire 1 : qb $end
$var wire 1 p qb_m $end
$var wire 1 V r $end
$var wire 1 W s $end
$scope module master $end
$var wire 1 Y g $end
$var wire 1 o q $end
$var wire 1 p qb $end
$var wire 1 V r $end
$var wire 1 W s $end
$var wire 1 q x $end
$var wire 1 r y $end
$upscope $end
$scope module slave $end
$var wire 1 n g $end
$var wire 1 & q $end
$var wire 1 : qb $end
$var wire 1 p r $end
$var wire 1 o s $end
$var wire 1 s x $end
$var wire 1 t y $end
$upscope $end
$upscope $end
$scope module ff7 $end
$var wire 1 Y clk $end
$var wire 1 ! q $end
$var wire 1 5 qb $end
$var wire 1 u qr $end
$var wire 1 v qrb $end
$var wire 1 w qs $end
$var wire 1 x qsb $end
$var wire 1 V r $end
$var wire 1 y rblk $end
$var wire 1 W s $end
$var wire 1 z sblk $end
$upscope $end
$scope module ff8 $end
$var wire 1 { aux_q $end
$var wire 1 | aux_qb $end
$var wire 1 2 q $end
$var wire 1 F qb $end
$var wire 1 V r $end
$var wire 1 W s $end
$var reg 64 } Ts_q [63:0] $end
$upscope $end
$scope module ff9 $end
$var wire 1 Y g $end
$var wire 1 - q $end
$var wire 1 A qb $end
$var wire 1 V r $end
$var wire 1 W s $end
$var wire 1 ~ x $end
$var wire 1 !" y $end
$upscope $end
$scope module ff10 $end
$var wire 1 Y clk $end
$var wire 1 "" clkb $end
$var wire 1 ( q $end
$var wire 1 #" q_m $end
$var wire 1 < qb $end
$var wire 1 $" qb_m $end
$var wire 1 V r $end
$var wire 1 W s $end
$scope module master $end
$var wire 1 Y g $end
$var wire 1 #" q $end
$var wire 1 $" qb $end
$var wire 1 V r $end
$var wire 1 W s $end
$var wire 1 %" x $end
$var wire 1 &" y $end
$upscope $end
$scope module slave $end
$var wire 1 "" g $end
$var wire 1 ( q $end
$var wire 1 < qb $end
$var wire 1 $" r $end
$var wire 1 #" s $end
$var wire 1 '" x $end
$var wire 1 (" y $end
$upscope $end
$upscope $end
$scope module ff11 $end
$var wire 1 Y clk $end
$var wire 1 # q $end
$var wire 1 7 qb $end
$var wire 1 )" qr $end
$var wire 1 *" qrb $end
$var wire 1 +" qs $end
$var wire 1 ," qsb $end
$var wire 1 V r $end
$var wire 1 -" rblk $end
$var wire 1 W s $end
$var wire 1 ." sblk $end
$upscope $end
$scope module ff12 $end
$var wire 1 /" aux_q $end
$var wire 1 0" aux_qb $end
$var wire 1 1 q $end
$var wire 1 E qb $end
$var wire 1 V r $end
$var wire 1 W s $end
$var reg 64 1" Ts_q [63:0] $end
$upscope $end
$scope module ff13 $end
$var wire 1 Y g $end
$var wire 1 , q $end
$var wire 1 @ qb $end
$var wire 1 V r $end
$var wire 1 W s $end
$var wire 1 2" x $end
$var wire 1 3" y $end
$upscope $end
$scope module ff14 $end
$var wire 1 Y clk $end
$var wire 1 4" clkb $end
$var wire 1 ' q $end
$var wire 1 5" q_m $end
$var wire 1 ; qb $end
$var wire 1 6" qb_m $end
$var wire 1 V r $end
$var wire 1 W s $end
$scope module master $end
$var wire 1 Y g $end
$var wire 1 5" q $end
$var wire 1 6" qb $end
$var wire 1 V r $end
$var wire 1 W s $end
$var wire 1 7" x $end
$var wire 1 8" y $end
$upscope $end
$scope module slave $end
$var wire 1 4" g $end
$var wire 1 ' q $end
$var wire 1 ; qb $end
$var wire 1 6" r $end
$var wire 1 5" s $end
$var wire 1 9" x $end
$var wire 1 :" y $end
$upscope $end
$upscope $end
$scope module ff15 $end
$var wire 1 Y clk $end
$var wire 1 " q $end
$var wire 1 6 qb $end
$var wire 1 ;" qr $end
$var wire 1 <" qrb $end
$var wire 1 =" qs $end
$var wire 1 >" qsb $end
$var wire 1 V r $end
$var wire 1 ?" rblk $end
$var wire 1 W s $end
$var wire 1 @" sblk $end
$upscope $end
$scope module ff16 $end
$var wire 1 A" aux_q $end
$var wire 1 B" aux_qb $end
$var wire 1 3 q $end
$var wire 1 G qb $end
$var wire 1 V r $end
$var wire 1 W s $end
$var reg 64 C" Ts_q [63:0] $end
$upscope $end
$scope module ff17 $end
$var wire 1 Y g $end
$var wire 1 . q $end
$var wire 1 B qb $end
$var wire 1 V r $end
$var wire 1 W s $end
$var wire 1 D" x $end
$var wire 1 E" y $end
$upscope $end
$scope module ff18 $end
$var wire 1 Y clk $end
$var wire 1 F" clkb $end
$var wire 1 ) q $end
$var wire 1 G" q_m $end
$var wire 1 = qb $end
$var wire 1 H" qb_m $end
$var wire 1 V r $end
$var wire 1 W s $end
$scope module master $end
$var wire 1 Y g $end
$var wire 1 G" q $end
$var wire 1 H" qb $end
$var wire 1 V r $end
$var wire 1 W s $end
$var wire 1 I" x $end
$var wire 1 J" y $end
$upscope $end
$scope module slave $end
$var wire 1 F" g $end
$var wire 1 ) q $end
$var wire 1 = qb $end
$var wire 1 H" r $end
$var wire 1 G" s $end
$var wire 1 K" x $end
$var wire 1 L" y $end
$upscope $end
$upscope $end
$scope module ff19 $end
$var wire 1 Y clk $end
$var wire 1 $ q $end
$var wire 1 8 qb $end
$var wire 1 M" qr $end
$var wire 1 N" qrb $end
$var wire 1 O" qs $end
$var wire 1 P" qsb $end
$var wire 1 V r $end
$var wire 1 Q" rblk $end
$var wire 1 W s $end
$var wire 1 R" sblk $end
$upscope $end
$upscope $end
$enddefinitions $end
#0
$dumpvars
xR"
xQ"
xP"
xO"
xN"
xM"
xL"
xK"
xJ"
xI"
xH"
xG"
xF"
xE"
xD"
bx C"
xB"
xA"
x@"
x?"
x>"
x="
x<"
x;"
x:"
x9"
x8"
x7"
x6"
x5"
x4"
x3"
x2"
bx 1"
x0"
x/"
x."
x-"
x,"
x+"
x*"
x)"
x("
x'"
x&"
x%"
x$"
x#"
x""
x!"
x~
bx }
x|
x{
xz
xy
xx
xw
xv
xu
xt
xs
xr
xq
xp
xo
xn
xm
xl
bx k
xj
xi
xh
xg
xf
xe
xd
xc
xb
xa
x`
x_
x^
x]
x\
x[
xZ
xY
bx X
xW
xV
xU
xT
xS
xR
xQ
xP
xO
bx N
xM
b0 L
bx K
b0 J
bx I
xH
xG
xF
xE
xD
xC
xB
xA
x@
x?
x>
x=
x<
x;
x:
x9
x8
x7
x6
x5
x4
x3
x2
x1
x0
x/
x.
x-
x,
x+
x*
x)
x(
x'
x&
x%
x$
x#
x"
x!
$end
#1000
b1111101000 J
b1111101000 L
1S
0R
b1111101000 K
1P
b1111101000 I
0Q
0W
1O
1V
1M
1Y
b0 N
#1019
0T
0d
0h
0i
0v
0z
0{
0*"
0."
0/"
0<"
0@"
0A"
0N"
0R"
0Z
1[
0\
0_
1`
0e
0c
0l
1m
0n
0q
1r
0w
0u
0~
1!"
0""
0%"
1&"
0+"
0)"
02"
13"
04"
07"
18"
0="
0;"
0D"
1E"
0F"
0I"
1J"
0O"
0M"
#1020
04
00
01
#1021
02
0M
0Y
#1038
0a
0b
1f
0s
0t
1x
0'"
0("
1,"
09"
0:"
1>"
0K"
0L"
1P"
#1039
1U
1j
10"
0/
0]
0+
0o
0,
05"
#1040
1|
0[
1\
0`
1c
0m
1n
0r
1u
0!"
1""
0&"
1)"
03"
14"
08"
1;"
0E"
1F"
0J"
1M"
1H
0-
0#"
#1041
1F
1D
#1059
xb
xt
x("
x:"
xK"
xL"
1C
1^
#1060
0%
x+
xo
0!
x,
x5"
0"
1A
1$"
1?
1p
#1061
0#
#1066
03
#1078
1b
#1079
1g
xs
1y
x9"
1?"
1("
1t
#1080
1-"
19
0+
0o
#1081
17
15
#1085
1B"
#1086
1G
1E
#1098
0*
#1099
0s
0&
#1100
0(
#1106
0$
#1118
1>
#1120
1<
1:
#1125
1Q"
#1126
18
16
#2000
b11111010000 L
0S
1R
b11111010000 K
1Q
1W
b1 N
1M
1Y
#2019
0U
1Z
1_
0f
0g
0j
1l
1q
0x
0y
0|
1~
1%"
0,"
0-"
00"
12"
17"
0>"
0?"
0B"
1D"
1I"
0P"
0Q"
1[
0\
1`
0c
1m
0n
1r
0u
1!"
0""
1&"
0)"
13"
04"
18"
0;"
1E"
0F"
1J"
0M"
#2020
0H
0F
0G
#2021
0D
0M
0Y
#2038
0b
0t
0("
09"
0:"
0K"
0L"
#2039
0C
0^
0A
0$"
0B
0H"
0,
05"
#2040
0Z
0[
1\
0_
0`
1e
1c
0l
0m
1n
0q
0r
1w
1u
0~
0!"
1""
0%"
0&"
1+"
1)"
02"
03"
14"
07"
08"
1="
1;"
0D"
0E"
1F"
0I"
0J"
1O"
1M"
0?
0p
#2059
0c
0e
0u
0w
0)"
0+"
x:"
0;"
0="
xK"
0M"
0O"
#2060
1C
1/
1^
1]
1A
1$"
x,
x5"
xB
xH"
1+
1o
#2066
0E
#2078
1e
1c
1w
1u
1+"
1)"
1="
1;"
1O"
1M"
#2079
1b
1a
1("
x9"
xL"
1s
#2080
0/
0C
0]
0^
#2097
0c
0e
0u
0w
0)"
0+"
0;"
0="
0M"
0O"
#2099
0a
0b
0>
#2100
1C
1/
1^
1]
0:
#2116
1e
1c
1w
1u
1+"
1)"
1="
1;"
1O"
1M"
#2119
1b
1a
1>
1*
#2120
0/
0C
0]
0^
1&
#2135
0c
0e
0u
0w
0)"
0+"
0;"
0="
0M"
0O"
#2139
0a
0b
0*
0>
#2140
1C
1/
1^
1]
#2154
1e
1c
1w
1u
1+"
1)"
1="
1;"
1O"
1M"
#2159
1b
1a
1>
1*
#2160
0/
0C
0]
0^
#2173
0c
0e
0u
0w
0)"
0+"
0;"
0="
0M"
0O"
#2179
0a
0b
0*
0>
#2180
1C
1/
1^
1]
#2192
1e
1c
1w
1u
1+"
1)"
1="
1;"
1O"
1M"
#2199
1b
1a
1>
1*
#2200
0/
0C
0]
0^
#2211
0c
0e
0u
0w
0)"
0+"
0;"
0="
0M"
0O"
#2219
0a
0b
0*
0>
#2220
1C
1/
1^
1]
#2230
1e
1c
1w
1u
1+"
1)"
1="
1;"
1O"
1M"
#2239
1b
1a
1>
1*
#2240
0/
0C
0]
0^
#2249
0c
0e
0u
0w
0)"
0+"
0;"
0="
0M"
0O"
#2259
0a
0b
0*
0>
#2260
1C
1/
1^
1]
#2268
1e
1c
1w
1u
1+"
1)"
1="
1;"
1O"
1M"
#2279
1b
1a
1>
1*
#2280
0/
0C
0]
0^
#2287
0c
0e
0u
0w
0)"
0+"
0;"
0="
0M"
0O"
#2299
0a
0b
0*
0>
#2300
1C
1/
1^
1]
#2306
1e
1c
1w
1u
1+"
1)"
1="
1;"
1O"
1M"
#2319
1b
1a
1>
1*
#2320
0/
0C
0]
0^
#2325
0c
0e
0u
0w
0)"
0+"
0;"
0="
0M"
0O"
#2339
0a
0b
0*
0>
#2340
1C
1/
1^
1]
#2344
1e
1c
1w
1u
1+"
1)"
1="
1;"
1O"
1M"
#2359
1b
1a
1>
1*
#2360
0/
0C
0]
0^
#2363
0c
0e
0u
0w
0)"
0+"
0;"
0="
0M"
0O"
#2379
0a
0b
0*
0>
#2380
1C
1/
1^
1]
#2382
1e
1c
1w
1u
1+"
1)"
1="
1;"
1O"
1M"
#2399
1b
1a
1>
1*
#2400
0/
0C
0]
0^
#2401
0c
0e
0u
0w
0)"
0+"
0;"
0="
0M"
0O"
#2419
0a
0b
0*
0>
#2420
1e
1c
1w
1u
1+"
1)"
1="
1;"
1O"
1M"
1C
1/
1^
1]
#2439
0c
0e
0u
0w
0)"
0+"
0;"
0="
0M"
0O"
1b
1a
1>
1*
#2440
0/
0C
0]
0^
#2458
1e
1c
1w
1u
1+"
1)"
1="
1;"
1O"
1M"
#2459
0a
0b
0*
0>
#2460
1C
1/
1^
1]
#2477
0c
0e
0u
0w
0)"
0+"
0;"
0="
0M"
0O"
#2479
1b
1a
1>
1*
#2480
0/
0C
0]
0^
#2496
1e
1c
1w
1u
1+"
1)"
1="
1;"
1O"
1M"
#2499
0a
0b
0*
0>
#2500
1C
1/
1^
1]
#2515
0c
0e
0u
0w
0)"
0+"
0;"
0="
0M"
0O"
#2519
1b
1a
1>
1*
#2520
0/
0C
0]
0^
#2534
1e
1c
1w
1u
1+"
1)"
1="
1;"
1O"
1M"
#2539
0a
0b
0*
0>
#2540
1C
1/
1^
1]
#2553
0c
0e
0u
0w
0)"
0+"
0;"
0="
0M"
0O"
#2559
1b
1a
1>
1*
#2560
0/
0C
0]
0^
#2572
1e
1c
1w
1u
1+"
1)"
1="
1;"
1O"
1M"
#2579
0a
0b
0*
0>
#2580
1C
1/
1^
1]
#2591
0c
0e
0u
0w
0)"
0+"
0;"
0="
0M"
0O"
#2599
1b
1a
1>
1*
#2600
0/
0C
0]
0^
#2610
1e
1c
1w
1u
1+"
1)"
1="
1;"
1O"
1M"
#2619
0a
0b
0*
0>
#2620
1C
1/
1^
1]
#2629
0c
0e
0u
0w
0)"
0+"
0;"
0="
0M"
0O"
#2639
1b
1a
1>
1*
#2640
0/
0C
0]
0^
#2648
1e
1c
1w
1u
1+"
1)"
1="
1;"
1O"
1M"
#2659
0a
0b
0*
0>
#2660
1C
1/
1^
1]
#2667
0c
0e
0u
0w
0)"
0+"
0;"
0="
0M"
0O"
#2679
1b
1a
1>
1*
#2680
0/
0C
0]
0^
#2686
1e
1c
1w
1u
1+"
1)"
1="
1;"
1O"
1M"
#2699
0a
0b
0*
0>
#2700
1C
1/
1^
1]
#2705
0c
0e
0u
0w
0)"
0+"
0;"
0="
0M"
0O"
#2719
1b
1a
1>
1*
#2720
0/
0C
0]
0^
#2724
1e
1c
1w
1u
1+"
1)"
1="
1;"
1O"
1M"
#2739
0a
0b
0*
0>
#2740
1C
1/
1^
1]
#2743
0c
0e
0u
0w
0)"
0+"
0;"
0="
0M"
0O"
#2759
1b
1a
1>
1*
#2760
0/
0C
0]
0^
#2762
1e
1c
1w
1u
1+"
1)"
1="
1;"
1O"
1M"
#2779
0a
0b
0*
0>
#2780
1C
1/
1^
1]
#2781
0c
0e
0u
0w
0)"
0+"
0;"
0="
0M"
0O"
#2799
1b
1a
1>
1*
#2800
1e
1c
1w
1u
1+"
1)"
1="
1;"
1O"
1M"
0/
0C
0]
0^
#2819
0c
0e
0u
0w
0)"
0+"
0;"
0="
0M"
0O"
0a
0b
0*
0>
#2820
1C
1/
1^
1]
#2838
1e
1c
1w
1u
1+"
1)"
1="
1;"
1O"
1M"
#2839
1b
1a
1>
1*
#2840
0/
0C
0]
0^
#2857
0c
0e
0u
0w
0)"
0+"
0;"
0="
0M"
0O"
#2859
0a
0b
0*
0>
#2860
1C
1/
1^
1]
#2876
1e
1c
1w
1u
1+"
1)"
1="
1;"
1O"
1M"
#2879
1b
1a
1>
1*
#2880
0/
0C
0]
0^
#2895
0c
0e
0u
0w
0)"
0+"
0;"
0="
0M"
0O"
#2899
0a
0b
0*
0>
#2900
1C
1/
1^
1]
#2914
1e
1c
1w
1u
1+"
1)"
1="
1;"
1O"
1M"
#2919
1b
1a
1>
1*
#2920
0/
0C
0]
0^
#2933
0c
0e
0u
0w
0)"
0+"
0;"
0="
0M"
0O"
#2939
0a
0b
0*
0>
#2940
1C
1/
1^
1]
#2952
1e
1c
1w
1u
1+"
1)"
1="
1;"
1O"
1M"
#2959
1b
1a
1>
1*
#2960
0/
0C
0]
0^
#2971
0c
0e
0u
0w
0)"
0+"
0;"
0="
0M"
0O"
#2979
0a
0b
0*
0>
#2980
1C
1/
1^
1]
#2990
1e
1c
1w
1u
1+"
1)"
1="
1;"
1O"
1M"
#2999
1b
1a
1>
1*
#3000
b101110111000 J
0P
b101110111000 I
0O
0V
0/
0C
0]
0^
b10 N
1M
1Y
#3009
0c
0e
0u
0w
0)"
0+"
0;"
0="
0M"
0O"
#3019
1T
1i
1{
1/"
1A"
0a
0b
1Z
0\
1_
1l
0n
1q
1~
0""
1%"
12"
04"
17"
1D"
0F"
1I"
0*
0>
#3020
14
10
11
1/
1]
#3021
12
0M
0Y
#3028
1d
1v
1*"
1<"
1N"
#3038
0s
0("
09"
0:"
0K"
0L"
#3039
0A
0$"
0B
0H"
1>
1*
#3040
0Z
1\
0_
1e
0l
1n
0q
1w
0~
1""
0%"
1+"
02"
14"
07"
1="
0D"
1F"
0I"
1O"
#3059
1a
1s
x9"
x:"
xK"
0*
0>
#3060
09
1A
1$"
07
xB
xH"
08
1-
1#"
#3061
05
#3066
13
#3079
1h
1("
1."
xL"
1R"
1'"
1*
#3080
1z
1%
0A
0$"
#3081
1!
1#
#3099
0("
0<
#3106
06
#3120
1(
#3125
1@"
#3126
1"
1$
#4000
b111110100000 L
0R
b111110100000 K
0Q
0W
b11 N
1M
1Y
#4019
0\
0e
0n
0w
0""
0+"
04"
0="
0F"
0O"
#4021
0M
0Y
