materia_clase/Apuntes_de_Clase/Simuladores/Verilogger/test_bToESeg.v
module test_bToESeg (eSeg, A, B, C, D);
  input eSeg;
  output A, B, C, D;
  reg A, B, C, D;

  initial // two slashes introduce a single line comment
    begin
      $monitor ($time,,
            "A = %b B = %b C = %b D = %b, eSeg = %b",
             A, B, C, D, eSeg);
      $dumpfile("eSeg.vcd"); //Define el nombre del archivo vcd
      $dumpvars;             //Salva los estados de todas las variables

      //waveform for simulating the nand lip lop
      #10 A = 0; B = 0; C = 0; D = 0;
      #10 D = 1;
      #10 C = 1; D = 0;
      #10 $finish;
    end

endmodule

materia_clase/Apuntes_de_Clase/Simuladores/Verilogger/binaryToESeg.v
module binaryToESeg (eSeg, A, B, C, D);
  output eSeg;
  input A, B, C, D;

  nand #1
    g1 (p1, C, ~D),
    g2 (p2, A, B),
    g3 (p3, ~B, ~D),
    g4 (p4, A, C),
    g5 (eSeg, p1, p2, p3, p4);

endmodule

materia_clase/Apuntes_de_Clase/Simuladores/Verilogger/testBench.v
module testBench;
  wire w1, w2, w3, w4, w5;

  binaryToESeg d (w1, w2, w3, w4, w5);
  test_bToESeg t (w1, w2, w3, w4, w5);

endmodule

materia_clase/Apuntes_de_Clase/Simuladores/Verilogger/eSeg.vcd
$date
      Thu May 13 14:11:45 2004

$end
$version
      VeriLogger 6.6a
$end
$timescale
      1ns
$end


$scope module testBench $end
$var wire      1 !    w1  $end
$var wire      1 "    w2  $end
$var wire      1 #    w3  $end
$var wire      1 $    w4  $end
$var wire      1 %    w5  $end

$scope module t $end
$var wire      1 &    eSeg  $end
$var reg       1 '    A  $end
$var reg       1 (    B  $end
$var reg       1 )    C  $end
$var reg       1 *    D  $end
$upscope $end


$scope module d $end
$var wire      1 +    D  $end
$var wire      1 ,    C  $end
$var wire      1 -    B  $end
$var wire      1 .    A  $end
$var wire      1 /    eSeg  $end
$var wire      1 0    p1  $end
$var wire      1 1    p2  $end
$var wire      1 2    p3  $end
$var wire      1 3    p4  $end
$upscope $end

$upscope $end

$enddefinitions      $end
$dumpvars
x3
x2
x1
x0
x/
x.
x-
x,
x+
x*
x)
x(
x'
x&
x%
x$
x#
x"
x!
$end
#10000
0'
0(
0)
0*
0.
0"
0-
0#
0,
0$
0+
0%
#11000
11
13
10
02
#12000
1&
1!
1/
#20000
1*
1+
1%
#21000
12
#22000
0&
0!
0/
#30000
1)
0*
1,
1$
0+
0%
#31000
00
02
#32000
1&
1!
1/
