materia_clase/Conceptos/Detalles_de_Temporizacion/Simulacion_SetUp_Hold/SetupHold.v
//`timescale 1us / 1ns

//D Latch
module DLatch (d, g, q, qb);
  parameter Ta = 1,
            Tb = 1,
            Tbas = 1;
  input d, g;
  output q, qb;
  wire db, s, r;
  
  //El latch con dos NOR
  nor #(Ta) c1 (qb, s, q);
  nor #(Tb) c2 (q, r, qb);
  //El control de entrada
  not #(Tbas) invD (db, d);
  and #(Tbas) gate1 (s,  d, g);
  and #(Tbas) gate2 (r, db, g);
  
endmodule

module GenG (g);
  parameter TH = 1, //Tiempo en alto
            TL = 2; //Tiempo en bajo
  output reg g;
  initial
    g = 0;
	
  always begin
    #TL g = 1;
	#TH g = 0;
  end
endmodule

module GenD (d);
  parameter TH = 1, //Tiempo en alto
            TL = 2; //Tiempo en bajo
  output reg d;
  
  initial begin
    d = 0;
  end
	
  always begin
    #TL d = 1;
	#TH d = 0;
	#1 d = 0;
  end
endmodule

//Top Module
module testbench;
  wire d, g;

  //Invocar una instancia del latch
  DLatch #(3, 3, 3) DL1 (d, g, q, qb);
  //Invocar los generadores de pulsos para datos y habilitacion del latch
  GenG #(15, 45) GenHabLatch (g);
  GenD #(30, 90) GenDato (d);

  initial
    begin
      //Prepare el archivo *.vcd
      $dumpfile ("SetUp_Hold.vcd");
      $dumpvars;
	  
	  #12000
	  $finish;

    end
endmodule

materia_clase/Conceptos/Detalles_de_Temporizacion/Simulacion_SetUp_Hold/SetUp_Hold.vcd
$date
	Fri Mar 20 07:40:14 2015
$end
$version
	Icarus Verilog
$end
$timescale
	1s
$end
$scope module testbench $end
$var wire 1 ! d $end
$var wire 1 " g $end
$var wire 1 # q $end
$var wire 1 $ qb $end
$scope module DL1 $end
$var wire 1 ! d $end
$var wire 1 % db $end
$var wire 1 " g $end
$var wire 1 # q $end
$var wire 1 $ qb $end
$var wire 1 & r $end
$var wire 1 ' s $end
$upscope $end
$scope module GenHabLatch $end
$var reg 1 ( g $end
$upscope $end
$scope module GenDato $end
$var reg 1 ) d $end
$upscope $end
$upscope $end
$enddefinitions $end
#0
$dumpvars
0)
0(
z'
z&
z%
x$
x#
0"
0!
$end
#3
0&
0'
1%
#45
1(
1"
#48
1&
#51
0#
#54
1$
#60
0(
0"
#63
0&
#90
1)
1!
#93
0%
#105
1(
1"
#108
1'
#111
0$
#114
1#
#120
0(
0"
0)
0!
#123
0'
1%
#165
1(
1"
#168
1&
#171
0#
#174
1$
#180
0(
0"
#183
0&
#211
1)
1!
#214
0%
#225
1(
1"
#228
1'
#231
0$
#234
1#
#240
0(
0"
#241
0)
0!
#243
0'
#244
1%
#285
1(
1"
#288
1&
#291
0#
#294
1$
#300
0(
0"
#303
0&
#332
1)
1!
#335
0%
#345
1(
1"
#348
1'
#351
0$
#354
1#
#360
0(
0"
#362
0)
0!
#363
0'
#365
1%
#405
1(
1"
#408
1&
#411
0#
#414
1$
#420
0(
0"
#423
0&
#453
1)
1!
#456
0%
#465
1(
1"
#468
1'
#471
0$
#474
1#
#480
0(
0"
#483
0'
0)
0!
#486
1%
#525
1(
1"
#528
1&
#531
0#
#534
1$
#540
0(
0"
#543
0&
#574
1)
1!
#577
0%
#585
1(
1"
#588
1'
#591
0$
#594
1#
#600
0(
0"
#603
0'
#604
0)
0!
#607
1%
#645
1(
1"
#648
1&
#651
0#
#654
1$
#660
0(
0"
#663
0&
#695
1)
1!
#698
0%
#705
1(
1"
#708
1'
#711
0$
#714
1#
#720
0(
0"
#723
0'
#725
0)
0!
#728
1%
#765
1(
1"
#768
1&
#771
0#
#774
1$
#780
0(
0"
#783
0&
#816
1)
1!
#819
0%
#825
1(
1"
#828
1'
#831
0$
#834
1#
#840
0(
0"
#843
0'
#846
0)
0!
#849
1%
#885
1(
1"
#888
1&
#891
0#
#894
1$
#900
0(
0"
#903
0&
#937
1)
1!
#940
0%
#945
1(
1"
#948
1'
#951
0$
#954
1#
#960
0(
0"
#963
0'
#967
0)
0!
#970
1%
#1005
1(
1"
#1008
1&
#1011
0#
#1014
1$
#1020
0(
0"
#1023
0&
#1058
1)
1!
#1061
0%
#1065
1(
1"
#1068
1'
#1071
0$
#1074
1#
#1080
0(
0"
#1083
0'
#1088
0)
0!
#1091
1%
#1125
1(
1"
#1128
1&
#1131
0#
#1134
1$
#1140
0(
0"
#1143
0&
#1179
1)
1!
#1182
0%
#1185
1(
1"
#1188
1'
#1191
0$
#1194
1#
#1200
0(
0"
#1203
0'
#1209
0)
0!
#1212
1%
#1245
1(
1"
#1248
1&
#1251
0#
#1254
1$
#1260
0(
0"
#1263
0&
#1300
1)
1!
#1303
0%
#1305
1(
1"
#1308
1'
#1311
0$
#1314
1#
#1320
0(
0"
#1323
0'
#1330
0)
0!
#1333
1%
#1365
1(
1"
#1368
1&
#1371
0#
#1374
1$
#1380
0(
0"
#1383
0&
#1421
1)
1!
#1424
0%
#1425
1(
1"
#1428
1'
#1431
0$
#1434
1#
#1440
0(
0"
#1443
0'
#1451
0)
0!
#1454
1%
#1485
1(
1"
#1488
1&
#1491
0#
#1494
1$
#1500
0(
0"
#1503
0&
#1542
1)
1!
#1545
0%
1(
1"
#1548
1'
#1551
0$
#1554
1#
#1560
0(
0"
#1563
0'
#1572
0)
0!
#1575
1%
#1605
1(
1"
#1608
1&
#1611
0#
#1614
1$
#1620
0(
0"
#1623
0&
#1663
1)
1!
#1665
1(
1"
#1666
0%
#1668
1'
#1671
0$
#1674
1#
#1680
0(
0"
#1683
0'
#1693
0)
0!
#1696
1%
#1725
1(
1"
#1728
1&
#1731
0#
#1734
1$
#1740
0(
0"
#1743
0&
#1784
1)
1!
#1785
1(
1"
#1787
0%
#1788
1'
#1791
0$
#1794
1#
#1800
0(
0"
#1803
0'
#1814
0)
0!
#1817
1%
#1845
1(
1"
#1848
1&
#1851
0#
#1854
1$
#1860
0(
0"
#1863
0&
#1905
1(
1"
1)
1!
#1908
1&
1'
0%
#1911
0$
0&
#1914
1#
#1920
0(
0"
#1923
0'
#1935
0)
0!
#1938
1%
#1965
1(
1"
#1968
1&
#1971
0#
#1974
1$
#1980
0(
0"
#1983
0&
#2025
1(
1"
#2026
1)
1!
#2028
1&
#2029
1'
0%
#2032
0$
0&
#2035
1#
#2040
0(
0"
#2043
0'
#2056
0)
0!
#2059
1%
#2085
1(
1"
#2088
1&
#2091
0#
#2094
1$
#2100
0(
0"
#2103
0&
#2145
1(
1"
#2147
1)
1!
#2148
1&
#2150
1'
0%
#2153
0$
0&
#2156
1#
#2160
0(
0"
#2163
0'
#2177
0)
0!
#2180
1%
#2205
1(
1"
#2208
1&
#2211
0#
#2214
1$
#2220
0(
0"
#2223
0&
#2265
1(
1"
#2268
1&
1)
1!
#2271
1'
0%
#2274
0$
0&
#2277
1#
#2280
0(
0"
#2283
0'
#2298
0)
0!
#2301
1%
#2325
1(
1"
#2328
1&
#2331
0#
#2334
1$
#2340
0(
0"
#2343
0&
#2385
1(
1"
#2388
1&
#2389
1)
1!
#2392
1'
0%
#2395
0$
0&
#2398
1#
#2400
0(
0"
#2403
0'
#2419
0)
0!
#2422
1%
#2445
1(
1"
#2448
1&
#2451
0#
#2454
1$
#2460
0(
0"
#2463
0&
#2505
1(
1"
#2508
1&
#2510
1)
1!
#2513
1'
0%
#2516
0$
0&
#2519
1#
#2520
0(
0"
#2523
0'
#2540
0)
0!
#2543
1%
#2565
1(
1"
#2568
1&
#2571
0#
#2574
1$
#2580
0(
0"
#2583
0&
#2625
1(
1"
#2628
1&
#2631
1)
1!
#2634
1'
0%
#2637
0$
0&
#2640
1#
0(
0"
#2643
0'
#2661
0)
0!
#2664
1%
#2685
1(
1"
#2688
1&
#2691
0#
#2694
1$
#2700
0(
0"
#2703
0&
#2745
1(
1"
#2748
1&
#2752
1)
1!
#2755
1'
0%
#2758
0$
0&
#2760
0(
0"
#2761
1#
#2763
0'
#2782
0)
0!
#2785
1%
#2805
1(
1"
#2808
1&
#2811
0#
#2814
1$
#2820
0(
0"
#2823
0&
#2865
1(
1"
#2868
1&
#2873
1)
1!
#2876
1'
0%
#2879
0$
0&
#2880
0(
0"
#2882
1#
#2883
0'
#2903
0)
0!
#2906
1%
#2925
1(
1"
#2928
1&
#2931
0#
#2934
1$
#2940
0(
0"
#2943
0&
#2985
1(
1"
#2988
1&
#2994
1)
1!
#2997
1'
0%
#3000
0$
0&
0(
0"
#3003
1#
0'
#3024
0)
0!
#3027
1%
#3045
1(
1"
#3048
1&
#3051
0#
#3054
1$
#3060
0(
0"
#3063
0&
#3105
1(
1"
#3108
1&
#3115
1)
1!
#3118
1'
0%
#3120
0(
0"
#3121
0$
0&
#3123
0'
#3124
1#
#3145
0)
0!
#3148
1%
#3165
1(
1"
#3168
1&
#3171
0#
#3174
1$
#3180
0(
0"
#3183
0&
#3225
1(
1"
#3228
1&
#3236
1)
1!
#3239
1'
0%
#3240
0(
0"
#3242
0$
0&
#3243
0'
#3245
1#
#3266
0)
0!
#3269
1%
#3285
1(
1"
#3288
1&
#3291
0#
#3294
1$
#3300
0(
0"
#3303
0&
#3345
1(
1"
#3348
1&
#3357
1)
1!
#3360
1'
0%
0(
0"
#3363
0$
0&
0'
#3366
1#
1$
#3369
0$
0#
#3372
1#
1$
#3375
0$
0#
#3378
1#
1$
#3381
0$
0#
#3384
1#
1$
#3387
0$
0#
0)
0!
#3390
1#
1$
1%
#3393
0$
0#
#3396
1#
1$
#3399
0$
0#
#3402
1#
1$
#3405
0$
0#
1(
1"
#3408
1#
1$
1&
#3411
0$
0#
#3414
1$
#3420
0(
0"
#3423
0&
#3465
1(
1"
#3468
1&
#3478
1)
1!
#3480
0(
0"
#3481
0%
#3483
0&
#3508
0)
0!
#3511
1%
#3525
1(
1"
#3528
1&
#3540
0(
0"
#3543
0&
#3585
1(
1"
#3588
1&
#3599
1)
1!
#3600
0(
0"
#3602
0%
#3603
0&
#3629
0)
0!
#3632
1%
#3645
1(
1"
#3648
1&
#3660
0(
0"
#3663
0&
#3705
1(
1"
#3708
1&
#3720
0(
0"
1)
1!
#3723
0&
0%
#3750
0)
0!
#3753
1%
#3765
1(
1"
#3768
1&
#3780
0(
0"
#3783
0&
#3825
1(
1"
#3828
1&
#3840
0(
0"
#3841
1)
1!
#3843
0&
#3844
0%
#3871
0)
0!
#3874
1%
#3885
1(
1"
#3888
1&
#3900
0(
0"
#3903
0&
#3945
1(
1"
#3948
1&
#3960
0(
0"
#3962
1)
1!
#3963
0&
#3965
0%
#3992
0)
0!
#3995
1%
#4005
1(
1"
#4008
1&
#4020
0(
0"
#4023
0&
#4065
1(
1"
#4068
1&
#4080
0(
0"
#4083
0&
1)
1!
#4086
0%
#4113
0)
0!
#4116
1%
#4125
1(
1"
#4128
1&
#4140
0(
0"
#4143
0&
#4185
1(
1"
#4188
1&
#4200
0(
0"
#4203
0&
#4204
1)
1!
#4207
0%
#4234
0)
0!
#4237
1%
#4245
1(
1"
#4248
1&
#4260
0(
0"
#4263
0&
#4305
1(
1"
#4308
1&
#4320
0(
0"
#4323
0&
#4325
1)
1!
#4328
0%
#4355
0)
0!
#4358
1%
#4365
1(
1"
#4368
1&
#4380
0(
0"
#4383
0&
#4425
1(
1"
#4428
1&
#4440
0(
0"
#4443
0&
#4446
1)
1!
#4449
0%
#4476
0)
0!
#4479
1%
#4485
1(
1"
#4488
1&
#4500
0(
0"
#4503
0&
#4545
1(
1"
#4548
1&
#4560
0(
0"
#4563
0&
#4567
1)
1!
#4570
0%
#4597
0)
0!
#4600
1%
#4605
1(
1"
#4608
1&
#4620
0(
0"
#4623
0&
#4665
1(
1"
#4668
1&
#4680
0(
0"
#4683
0&
#4688
1)
1!
#4691
0%
#4718
0)
0!
#4721
1%
#4725
1(
1"
#4728
1&
#4740
0(
0"
#4743
0&
#4785
1(
1"
#4788
1&
#4800
0(
0"
#4803
0&
#4809
1)
1!
#4812
0%
#4839
0)
0!
#4842
1%
#4845
1(
1"
#4848
1&
#4860
0(
0"
#4863
0&
#4905
1(
1"
#4908
1&
#4920
0(
0"
#4923
0&
#4930
1)
1!
#4933
0%
#4960
0)
0!
#4963
1%
#4965
1(
1"
#4968
1&
#4980
0(
0"
#4983
0&
#5025
1(
1"
#5028
1&
#5040
0(
0"
#5043
0&
#5051
1)
1!
#5054
0%
#5081
0)
0!
#5084
1%
#5085
1(
1"
#5088
1&
#5100
0(
0"
#5103
0&
#5145
1(
1"
#5148
1&
#5160
0(
0"
#5163
0&
#5172
1)
1!
#5175
0%
#5202
0)
0!
#5205
1%
1(
1"
#5208
1&
#5220
0(
0"
#5223
0&
#5265
1(
1"
#5268
1&
#5280
0(
0"
#5283
0&
#5293
1)
1!
#5296
0%
#5323
0)
0!
#5325
1(
1"
#5326
1%
#5329
1&
#5340
0(
0"
#5343
0&
#5385
1(
1"
#5388
1&
#5400
0(
0"
#5403
0&
#5414
1)
1!
#5417
0%
#5444
0)
0!
#5445
1(
1"
#5447
1%
#5450
1&
#5460
0(
0"
#5463
0&
#5505
1(
1"
#5508
1&
#5520
0(
0"
#5523
0&
#5535
1)
1!
#5538
0%
#5565
0)
0!
1(
1"
#5568
1%
#5571
1&
#5580
0(
0"
#5583
0&
#5625
1(
1"
#5628
1&
#5640
0(
0"
#5643
0&
#5656
1)
1!
#5659
0%
#5685
1(
1"
#5686
0)
0!
#5689
1%
#5692
1&
#5700
0(
0"
#5703
0&
#5745
1(
1"
#5748
1&
#5760
0(
0"
#5763
0&
#5777
1)
1!
#5780
0%
#5805
1(
1"
#5807
0)
0!
#5810
1%
#5813
1&
#5820
0(
0"
#5823
0&
#5865
1(
1"
#5868
1&
#5880
0(
0"
#5883
0&
#5898
1)
1!
#5901
0%
#5925
1(
1"
#5928
1'
0)
0!
#5931
0$
0'
1%
#5934
1#
1$
1&
#5937
0$
0#
#5940
1$
0(
0"
#5943
0&
#5985
1(
1"
#5988
1&
#6000
0(
0"
#6003
0&
#6019
1)
1!
#6022
0%
#6045
1(
1"
#6048
1'
#6049
0)
0!
#6051
0$
#6052
0'
1%
#6054
1#
#6055
1&
#6058
0#
#6060
0(
0"
#6061
1$
#6063
0&
#6105
1(
1"
#6108
1&
#6120
0(
0"
#6123
0&
#6140
1)
1!
#6143
0%
#6165
1(
1"
#6168
1'
#6170
0)
0!
#6171
0$
#6173
0'
1%
#6174
1#
#6176
1&
#6179
0#
#6180
0(
0"
#6182
1$
#6183
0&
#6225
1(
1"
#6228
1&
#6240
0(
0"
#6243
0&
#6261
1)
1!
#6264
0%
#6285
1(
1"
#6288
1'
#6291
0$
0)
0!
#6294
1#
0'
1%
#6297
1&
#6300
0#
0(
0"
#6303
1$
0&
#6345
1(
1"
#6348
1&
#6360
0(
0"
#6363
0&
#6382
1)
1!
#6385
0%
#6405
1(
1"
#6408
1'
#6411
0$
#6412
0)
0!
#6414
1#
#6415
0'
1%
#6418
1&
#6420
0(
0"
#6421
0#
#6423
0&
#6424
1$
#6465
1(
1"
#6468
1&
#6480
0(
0"
#6483
0&
#6503
1)
1!
#6506
0%
#6525
1(
1"
#6528
1'
#6531
0$
#6533
0)
0!
#6534
1#
#6536
0'
1%
#6539
1&
#6540
0(
0"
#6542
0#
#6543
0&
#6545
1$
#6585
1(
1"
#6588
1&
#6600
0(
0"
#6603
0&
#6624
1)
1!
#6627
0%
#6645
1(
1"
#6648
1'
#6651
0$
#6654
1#
0)
0!
#6657
0'
1%
#6660
1&
0(
0"
#6663
0#
0&
#6666
1$
1#
#6669
0#
0$
#6672
1$
1#
#6675
0#
0$
#6678
1$
1#
#6681
0#
0$
#6684
1$
1#
#6687
0#
0$
#6690
1$
1#
#6693
0#
0$
#6696
1$
1#
#6699
0#
0$
#6702
1$
1#
#6705
0#
0$
1(
1"
#6708
1$
1#
1&
#6711
0$
0#
#6714
1$
#6720
0(
0"
#6723
0&
#6745
1)
1!
#6748
0%
#6765
1(
1"
#6768
1'
#6771
0$
#6774
1#
#6775
0)
0!
#6778
0'
1%
#6780
0(
0"
#6825
1(
1"
#6828
1&
#6831
0#
#6834
1$
#6840
0(
0"
#6843
0&
#6866
1)
1!
#6869
0%
#6885
1(
1"
#6888
1'
#6891
0$
#6894
1#
#6896
0)
0!
#6899
0'
1%
#6900
0(
0"
#6945
1(
1"
#6948
1&
#6951
0#
#6954
1$
#6960
0(
0"
#6963
0&
#6987
1)
1!
#6990
0%
#7005
1(
1"
#7008
1'
#7011
0$
#7014
1#
#7017
0)
0!
#7020
0'
1%
0(
0"
#7065
1(
1"
#7068
1&
#7071
0#
#7074
1$
#7080
0(
0"
#7083
0&
#7108
1)
1!
#7111
0%
#7125
1(
1"
#7128
1'
#7131
0$
#7134
1#
#7138
0)
0!
#7140
0(
0"
#7141
0'
1%
#7185
1(
1"
#7188
1&
#7191
0#
#7194
1$
#7200
0(
0"
#7203
0&
#7229
1)
1!
#7232
0%
#7245
1(
1"
#7248
1'
#7251
0$
#7254
1#
#7259
0)
0!
#7260
0(
0"
#7262
0'
1%
#7305
1(
1"
#7308
1&
#7311
0#
#7314
1$
#7320
0(
0"
#7323
0&
#7350
1)
1!
#7353
0%
#7365
1(
1"
#7368
1'
#7371
0$
#7374
1#
#7380
0(
0"
0)
0!
#7383
0'
1%
#7425
1(
1"
#7428
1&
#7431
0#
#7434
1$
#7440
0(
0"
#7443
0&
#7471
1)
1!
#7474
0%
#7485
1(
1"
#7488
1'
#7491
0$
#7494
1#
#7500
0(
0"
#7501
0)
0!
#7503
0'
#7504
1%
#7545
1(
1"
#7548
1&
#7551
0#
#7554
1$
#7560
0(
0"
#7563
0&
#7592
1)
1!
#7595
0%
#7605
1(
1"
#7608
1'
#7611
0$
#7614
1#
#7620
0(
0"
#7622
0)
0!
#7623
0'
#7625
1%
#7665
1(
1"
#7668
1&
#7671
0#
#7674
1$
#7680
0(
0"
#7683
0&
#7713
1)
1!
#7716
0%
#7725
1(
1"
#7728
1'
#7731
0$
#7734
1#
#7740
0(
0"
#7743
0'
0)
0!
#7746
1%
#7785
1(
1"
#7788
1&
#7791
0#
#7794
1$
#7800
0(
0"
#7803
0&
#7834
1)
1!
#7837
0%
#7845
1(
1"
#7848
1'
#7851
0$
#7854
1#
#7860
0(
0"
#7863
0'
#7864
0)
0!
#7867
1%
#7905
1(
1"
#7908
1&
#7911
0#
#7914
1$
#7920
0(
0"
#7923
0&
#7955
1)
1!
#7958
0%
#7965
1(
1"
#7968
1'
#7971
0$
#7974
1#
#7980
0(
0"
#7983
0'
#7985
0)
0!
#7988
1%
#8025
1(
1"
#8028
1&
#8031
0#
#8034
1$
#8040
0(
0"
#8043
0&
#8076
1)
1!
#8079
0%
#8085
1(
1"
#8088
1'
#8091
0$
#8094
1#
#8100
0(
0"
#8103
0'
#8106
0)
0!
#8109
1%
#8145
1(
1"
#8148
1&
#8151
0#
#8154
1$
#8160
0(
0"
#8163
0&
#8197
1)
1!
#8200
0%
#8205
1(
1"
#8208
1'
#8211
0$
#8214
1#
#8220
0(
0"
#8223
0'
#8227
0)
0!
#8230
1%
#8265
1(
1"
#8268
1&
#8271
0#
#8274
1$
#8280
0(
0"
#8283
0&
#8318
1)
1!
#8321
0%
#8325
1(
1"
#8328
1'
#8331
0$
#8334
1#
#8340
0(
0"
#8343
0'
#8348
0)
0!
#8351
1%
#8385
1(
1"
#8388
1&
#8391
0#
#8394
1$
#8400
0(
0"
#8403
0&
#8439
1)
1!
#8442
0%
#8445
1(
1"
#8448
1'
#8451
0$
#8454
1#
#8460
0(
0"
#8463
0'
#8469
0)
0!
#8472
1%
#8505
1(
1"
#8508
1&
#8511
0#
#8514
1$
#8520
0(
0"
#8523
0&
#8560
1)
1!
#8563
0%
#8565
1(
1"
#8568
1'
#8571
0$
#8574
1#
#8580
0(
0"
#8583
0'
#8590
0)
0!
#8593
1%
#8625
1(
1"
#8628
1&
#8631
0#
#8634
1$
#8640
0(
0"
#8643
0&
#8681
1)
1!
#8684
0%
#8685
1(
1"
#8688
1'
#8691
0$
#8694
1#
#8700
0(
0"
#8703
0'
#8711
0)
0!
#8714
1%
#8745
1(
1"
#8748
1&
#8751
0#
#8754
1$
#8760
0(
0"
#8763
0&
#8802
1)
1!
#8805
0%
1(
1"
#8808
1'
#8811
0$
#8814
1#
#8820
0(
0"
#8823
0'
#8832
0)
0!
#8835
1%
#8865
1(
1"
#8868
1&
#8871
0#
#8874
1$
#8880
0(
0"
#8883
0&
#8923
1)
1!
#8925
1(
1"
#8926
0%
#8928
1'
#8931
0$
#8934
1#
#8940
0(
0"
#8943
0'
#8953
0)
0!
#8956
1%
#8985
1(
1"
#8988
1&
#8991
0#
#8994
1$
#9000
0(
0"
#9003
0&
#9044
1)
1!
#9045
1(
1"
#9047
0%
#9048
1'
#9051
0$
#9054
1#
#9060
0(
0"
#9063
0'
#9074
0)
0!
#9077
1%
#9105
1(
1"
#9108
1&
#9111
0#
#9114
1$
#9120
0(
0"
#9123
0&
#9165
1(
1"
1)
1!
#9168
1&
1'
0%
#9171
0$
0&
#9174
1#
#9180
0(
0"
#9183
0'
#9195
0)
0!
#9198
1%
#9225
1(
1"
#9228
1&
#9231
0#
#9234
1$
#9240
0(
0"
#9243
0&
#9285
1(
1"
#9286
1)
1!
#9288
1&
#9289
1'
0%
#9292
0$
0&
#9295
1#
#9300
0(
0"
#9303
0'
#9316
0)
0!
#9319
1%
#9345
1(
1"
#9348
1&
#9351
0#
#9354
1$
#9360
0(
0"
#9363
0&
#9405
1(
1"
#9407
1)
1!
#9408
1&
#9410
1'
0%
#9413
0$
0&
#9416
1#
#9420
0(
0"
#9423
0'
#9437
0)
0!
#9440
1%
#9465
1(
1"
#9468
1&
#9471
0#
#9474
1$
#9480
0(
0"
#9483
0&
#9525
1(
1"
#9528
1&
1)
1!
#9531
1'
0%
#9534
0$
0&
#9537
1#
#9540
0(
0"
#9543
0'
#9558
0)
0!
#9561
1%
#9585
1(
1"
#9588
1&
#9591
0#
#9594
1$
#9600
0(
0"
#9603
0&
#9645
1(
1"
#9648
1&
#9649
1)
1!
#9652
1'
0%
#9655
0$
0&
#9658
1#
#9660
0(
0"
#9663
0'
#9679
0)
0!
#9682
1%
#9705
1(
1"
#9708
1&
#9711
0#
#9714
1$
#9720
0(
0"
#9723
0&
#9765
1(
1"
#9768
1&
#9770
1)
1!
#9773
1'
0%
#9776
0$
0&
#9779
1#
#9780
0(
0"
#9783
0'
#9800
0)
0!
#9803
1%
#9825
1(
1"
#9828
1&
#9831
0#
#9834
1$
#9840
0(
0"
#9843
0&
#9885
1(
1"
#9888
1&
#9891
1)
1!
#9894
1'
0%
#9897
0$
0&
#9900
1#
0(
0"
#9903
0'
#9921
0)
0!
#9924
1%
#9945
1(
1"
#9948
1&
#9951
0#
#9954
1$
#9960
0(
0"
#9963
0&
#10005
1(
1"
#10008
1&
#10012
1)
1!
#10015
1'
0%
#10018
0$
0&
#10020
0(
0"
#10021
1#
#10023
0'
#10042
0)
0!
#10045
1%
#10065
1(
1"
#10068
1&
#10071
0#
#10074
1$
#10080
0(
0"
#10083
0&
#10125
1(
1"
#10128
1&
#10133
1)
1!
#10136
1'
0%
#10139
0$
0&
#10140
0(
0"
#10142
1#
#10143
0'
#10163
0)
0!
#10166
1%
#10185
1(
1"
#10188
1&
#10191
0#
#10194
1$
#10200
0(
0"
#10203
0&
#10245
1(
1"
#10248
1&
#10254
1)
1!
#10257
1'
0%
#10260
0$
0&
0(
0"
#10263
1#
0'
#10284
0)
0!
#10287
1%
#10305
1(
1"
#10308
1&
#10311
0#
#10314
1$
#10320
0(
0"
#10323
0&
#10365
1(
1"
#10368
1&
#10375
1)
1!
#10378
1'
0%
#10380
0(
0"
#10381
0$
0&
#10383
0'
#10384
1#
#10405
0)
0!
#10408
1%
#10425
1(
1"
#10428
1&
#10431
0#
#10434
1$
#10440
0(
0"
#10443
0&
#10485
1(
1"
#10488
1&
#10496
1)
1!
#10499
1'
0%
#10500
0(
0"
#10502
0$
0&
#10503
0'
#10505
1#
#10526
0)
0!
#10529
1%
#10545
1(
1"
#10548
1&
#10551
0#
#10554
1$
#10560
0(
0"
#10563
0&
#10605
1(
1"
#10608
1&
#10617
1)
1!
#10620
1'
0%
0(
0"
#10623
0$
0&
0'
#10626
1#
1$
#10629
0$
0#
#10632
1#
1$
#10635
0$
0#
#10638
1#
1$
#10641
0$
0#
#10644
1#
1$
#10647
0$
0#
0)
0!
#10650
1#
1$
1%
#10653
0$
0#
#10656
1#
1$
#10659
0$
0#
#10662
1#
1$
#10665
0$
0#
1(
1"
#10668
1#
1$
1&
#10671
0$
0#
#10674
1$
#10680
0(
0"
#10683
0&
#10725
1(
1"
#10728
1&
#10738
1)
1!
#10740
0(
0"
#10741
0%
#10743
0&
#10768
0)
0!
#10771
1%
#10785
1(
1"
#10788
1&
#10800
0(
0"
#10803
0&
#10845
1(
1"
#10848
1&
#10859
1)
1!
#10860
0(
0"
#10862
0%
#10863
0&
#10889
0)
0!
#10892
1%
#10905
1(
1"
#10908
1&
#10920
0(
0"
#10923
0&
#10965
1(
1"
#10968
1&
#10980
0(
0"
1)
1!
#10983
0&
0%
#11010
0)
0!
#11013
1%
#11025
1(
1"
#11028
1&
#11040
0(
0"
#11043
0&
#11085
1(
1"
#11088
1&
#11100
0(
0"
#11101
1)
1!
#11103
0&
#11104
0%
#11131
0)
0!
#11134
1%
#11145
1(
1"
#11148
1&
#11160
0(
0"
#11163
0&
#11205
1(
1"
#11208
1&
#11220
0(
0"
#11222
1)
1!
#11223
0&
#11225
0%
#11252
0)
0!
#11255
1%
#11265
1(
1"
#11268
1&
#11280
0(
0"
#11283
0&
#11325
1(
1"
#11328
1&
#11340
0(
0"
#11343
0&
1)
1!
#11346
0%
#11373
0)
0!
#11376
1%
#11385
1(
1"
#11388
1&
#11400
0(
0"
#11403
0&
#11445
1(
1"
#11448
1&
#11460
0(
0"
#11463
0&
#11464
1)
1!
#11467
0%
#11494
0)
0!
#11497
1%
#11505
1(
1"
#11508
1&
#11520
0(
0"
#11523
0&
#11565
1(
1"
#11568
1&
#11580
0(
0"
#11583
0&
#11585
1)
1!
#11588
0%
#11615
0)
0!
#11618
1%
#11625
1(
1"
#11628
1&
#11640
0(
0"
#11643
0&
#11685
1(
1"
#11688
1&
#11700
0(
0"
#11703
0&
#11706
1)
1!
#11709
0%
#11736
0)
0!
#11739
1%
#11745
1(
1"
#11748
1&
#11760
0(
0"
#11763
0&
#11805
1(
1"
#11808
1&
#11820
0(
0"
#11823
0&
#11827
1)
1!
#11830
0%
#11857
0)
0!
#11860
1%
#11865
1(
1"
#11868
1&
#11880
0(
0"
#11883
0&
#11925
1(
1"
#11928
1&
#11940
0(
0"
#11943
0&
#11948
1)
1!
#11951
0%
#11978
0)
0!
#11981
1%
#11985
1(
1"
#11988
1&
#12000
0(
0"
